{
  "proposals": [
    {
      "uid": "prop1",
      "aid": "prop-1",
      "text": "Proposal text",
      "workflowState": "published",
      "creator": "Användare (username)",
      "workflowApi": "#prop1"
    },
    {
      "uid": "prop2",
      "aid": "prop-2",
      "text": "Proposal text two",
      "workflowState": "denied",
      "creator": "Annan Användare (username-1)",
      "workflowApi": "#prop2"
    }
  ],
  "pollsOngoing": [
    {
      "title": "Omröstning 1",
      "uid": "123-asdf-312",
      "votes": 62,
      "potentialVotes": 134
    }
  ],
  "pollsClosed": [
    {
      "title": "Omröstning 0",
      "uid": "123-asdf-32312",
      "votes": 104,
      "potentialVotes": 134,
      "href": "/latest_poll_result.html"
    },
    {
      "title": "Omröstning 2",
      "uid": "123-asdf-32312kk",
      "votes": 124,
      "potentialVotes": 134,
      "href": "http://localhost:1234/"
    }
  ]
}